{
  "MainPageTitle": "JellyFish Lighting",
  "StatusTextLabel": "Status / Zones",
  "OnlineLabel": "Online / Brightness",
  "SettingsPageTitle": "Settings",
  "PollingSubheaderLabel": "WebSocket Polling",
  "UseSslLabel": "Use WSS",
  "UseSslSecondaryLabel": "Use secure websocket if supported",
  "PollIntervalLabel": "Poll interval (seconds)",
  "ButtonSettingsLabel": "Settings",
  "SaveButtonName": "Save",
  "RefreshNowLabel": "Refresh now",
  "GetPatternsAndZonesLabel": "Get patterns + zones",
  "PowerOnLabel": "Power on",
  "PowerOffLabel": "Power off",
  "SpeedLabel": "Speed",
  "CommonActionsSubheaderLabel": "Common actions",
  "PatternPathLabel": "Pattern path",
  "PatternPathHelpText": "Format: folder/pattern (example: Holidays/CandyCane)",
  "SelectedZonesLabel": "Selected zones",
  "SelectedZonesHelpText": "Comma-separated zone names (example: Front Roof,Garage)",
  "RequestedBrightnessLabel": "Brightness",
  "RequestedBrightnessHelpText": "Integer from 0 to 100. Requires requested pattern data.",
  "RequestedSpeedLabel": "Speed",
  "RequestedSpeedHelpText": "Integer >= 1. Requires requested pattern data.",
  "RequestPatternDataLabel": "Request pattern data",
  "RunSelectedPatternLabel": "Run selected pattern",
  "SetSelectedBrightnessLabel": "Set brightness",
  "SetSelectedSpeedLabel": "Set speed"
}
